stuom/__init__.py
stuom/duration.py
stuom/electricity.py
stuom/length.py
stuom/parse.py
stuom/uom.py
stuom/memory_size/__init__.py
stuom/memory_size/binary_memory_size.py
stuom/memory_size/decimal_memory_size.py
stuom/memory_size/memory_size.py
stuom-0.3.0.dist-info/licenses/LICENSE
stuom-0.3.0.dist-info/METADATA
stuom-0.3.0.dist-info/WHEEL
stuom-0.3.0.dist-info/top_level.txt
stuom-0.3.0.dist-info/RECORD
